CHANGELOG.md
progress_updater/__init__.py
progress_updater/backends/__init__.py
progress_updater/backends/base.py
progress_updater/backends/mongo.py
progress_updater/backends/redis.py
progress_updater/backends/sql.py
progress_updater/updater.py
progress_updater/utils.py
progress_updater-0.1.9.dist-info/LICENSE
progress_updater-0.1.9.dist-info/WHEEL
progress_updater-0.1.9.dist-info/METADATA
progress_updater-0.1.9.dist-info/RECORD
