Metadata-Version: 2.1
Name: progress-updater
Version: 0.1.9
Summary: Progress Updater
Home-page: https://github.com/pyprogrammerblog/progress-updater
License: LICENSE
Author: Jose Vazquez
Author-email: josevazjim88@gmail.com
Requires-Python: >=3.9,<4.0
Classifier: License :: OSI Approved :: MIT License
Classifier: License :: Other/Proprietary License
Classifier: Operating System :: OS Independent
Classifier: Programming Language :: Python :: 3
Classifier: Programming Language :: Python :: 3.10
Classifier: Programming Language :: Python :: 3.9
Requires-Dist: psycopg2 (>=2.9.3,<3.0.0)
Requires-Dist: psycopg2-binary (>=2.9.3,<3.0.0)
Requires-Dist: pydantic (>=1.10.1,<2.0.0)
Requires-Dist: pymongo (>=4.2.0,<5.0.0)
Requires-Dist: redis (>=4.3.4,<5.0.0)
Requires-Dist: sqlmodel (>=0.0.8,<0.0.9)
Project-URL: Documentation, https://progress-updater.readthedocs.io/en/latest/
